albert/__init__.py
albert/client.py
albert/exceptions.py
albert/collections/__init__.py
albert/collections/activities.py
albert/collections/attachments.py
albert/collections/base.py
albert/collections/batch_data.py
albert/collections/btdataset.py
albert/collections/btinsight.py
albert/collections/btmodel.py
albert/collections/cas.py
albert/collections/companies.py
albert/collections/custom_fields.py
albert/collections/custom_templates.py
albert/collections/data_columns.py
albert/collections/data_templates.py
albert/collections/entity_types.py
albert/collections/files.py
albert/collections/hazards.py
albert/collections/inventory.py
albert/collections/links.py
albert/collections/lists.py
albert/collections/locations.py
albert/collections/lots.py
albert/collections/notebooks.py
albert/collections/notes.py
albert/collections/parameter_groups.py
albert/collections/parameters.py
albert/collections/pricings.py
albert/collections/product_design.py
albert/collections/projects.py
albert/collections/property_data.py
albert/collections/report_templates.py
albert/collections/reports.py
albert/collections/roles.py
albert/collections/storage_classes.py
albert/collections/storage_locations.py
albert/collections/substance.py
albert/collections/synthesis.py
albert/collections/tags.py
albert/collections/tasks.py
albert/collections/un_numbers.py
albert/collections/units.py
albert/collections/users.py
albert/collections/workflows.py
albert/collections/worksheets.py
albert/core/__init__.py
albert/core/base.py
albert/core/logging.py
albert/core/pagination.py
albert/core/session.py
albert/core/auth/__init__.py
albert/core/auth/_listener.py
albert/core/auth/_manager.py
albert/core/auth/credentials.py
albert/core/auth/sso.py
albert/core/shared/__init__.py
albert/core/shared/enums.py
albert/core/shared/identifiers.py
albert/core/shared/types.py
albert/core/shared/models/base.py
albert/core/shared/models/patch.py
albert/resources/__init__.py
albert/resources/_mixins.py
albert-1.11.1.dist-info/METADATA
albert-1.11.1.dist-info/WHEEL
albert-1.11.1.dist-info/licenses/LICENSE
albert-1.11.1.dist-info/RECORD
