Metadata-Version: 2.4
Name: albert
Version: 1.11.1
Summary: The official Python SDK for the Albert Invent platform.
Project-URL: Homepage, https://www.albertinvent.com/
Project-URL: Documentation, https://docs.developer.albertinvent.com/albert-python
Project-URL: Repository, https://github.com/albert-labs/albert-python
Project-URL: Issues, https://github.com/albert-labs/albert-python/issues
Author-email: Albert Invent <support@albertinvent.com>
License: 
License-File: LICENSE
Keywords: API,Albert,Python,SDK
Classifier: Development Status :: 3 - Alpha
Classifier: License :: OSI Approved :: Apache Software License
Classifier: Operating System :: OS Independent
Classifier: Programming Language :: Python :: 3
Requires-Python: >=3.10
Requires-Dist: pandas<3,>=2.2.2
Requires-Dist: pydantic[email]<3,>=2.8.2
Requires-Dist: pyjwt<3,>=2.10.0
Requires-Dist: requests<3,>=2.32.3
Requires-Dist: tenacity>=8.2.3
